BIMFabrikHH_core/__init__.py
BIMFabrikHH_core/apps/__init__.py
BIMFabrikHH_core/apps/basepoint/__init__.py
BIMFabrikHH_core/apps/basepoint/basic/__init__.py
BIMFabrikHH_core/apps/basepoint/basic/app.py
BIMFabrikHH_core/apps/basepoint/generic/__init__.py
BIMFabrikHH_core/apps/basepoint/generic/basepoint_generic.py
BIMFabrikHH_core/apps/city/__init__.py
BIMFabrikHH_core/apps/city/app.py
BIMFabrikHH_core/apps/city/helpers.py
BIMFabrikHH_core/apps/city/parser.py
BIMFabrikHH_core/apps/interface.py
BIMFabrikHH_core/apps/terrain/__init__.py
BIMFabrikHH_core/apps/terrain/basic/__init__.py
BIMFabrikHH_core/apps/terrain/basic/app.py
BIMFabrikHH_core/apps/terrain/filtered/__init__.py
BIMFabrikHH_core/apps/terrain/filtered/app.py
BIMFabrikHH_core/apps/trees/__init__.py
BIMFabrikHH_core/apps/trees/basic/__init__.py
BIMFabrikHH_core/apps/trees/basic/app.py
BIMFabrikHH_core/apps/trees/basic/baum_col_names.py
BIMFabrikHH_core/apps/trees/basic/baum_manager.py
BIMFabrikHH_core/apps/trees/generic/__init__.py
BIMFabrikHH_core/apps/trees/generic/app.py
BIMFabrikHH_core/apps/trees/generic/app_pydantic.py
BIMFabrikHH_core/apps/trees/generic/tree_model.py
BIMFabrikHH_core/apps/trees/optimised/__init__.py
BIMFabrikHH_core/apps/trees/optimised/app.py
BIMFabrikHH_core/config/__init__.py
BIMFabrikHH_core/config/attribute_map.py
BIMFabrikHH_core/config/logging_colors.py
BIMFabrikHH_core/config/ogc_extractor.json
BIMFabrikHH_core/config/paths.py
BIMFabrikHH_core/core/__init__.py
BIMFabrikHH_core/core/data_processing/__init__.py
BIMFabrikHH_core/core/data_processing/data_processor.py
BIMFabrikHH_core/core/geometry/__init__.py
BIMFabrikHH_core/core/geometry/advanced_objects.py
BIMFabrikHH_core/core/geometry/city_furniture.py
BIMFabrikHH_core/core/geometry/standard_profiles.py
BIMFabrikHH_core/core/geometry/tree_objects.py
BIMFabrikHH_core/core/geometry/tree_objects_generic.py
BIMFabrikHH_core/core/georeferencing/__init__.py
BIMFabrikHH_core/core/georeferencing/crs_transform.py
bimfabrikhh_core-0.1.0.dist-info/METADATA
bimfabrikhh_core-0.1.0.dist-info/WHEEL
bimfabrikhh_core-0.1.0.dist-info/licenses/LICENSE
bimfabrikhh_core-0.1.0.dist-info/RECORD
