Metadata-Version: 2.4
Name: bimfabrikhh-core
Version: 0.1.0
Summary: Hamburg BIM Factory - Automated conversion of geospatial data to IFC format
License: LGPL-2.1
License-File: LICENSE
Keywords: BIM,IFC,CityGML,Hamburg,geospatial,terrain,trees
Author: Ahmed Salem
Author-email: ahmed.salem@gv.hamburg.de
Requires-Python: >=3.11,<3.12
Classifier: Development Status :: 4 - Beta
Classifier: Intended Audience :: Developers
Classifier: License :: OSI Approved
Classifier: License :: OSI Approved :: GNU Lesser General Public License v2 (LGPLv2)
Classifier: Programming Language :: Python :: 3
Classifier: Programming Language :: Python :: 3.11
Classifier: Topic :: Scientific/Engineering :: GIS
Provides-Extra: dev
Requires-Dist: icosphere (>=0.1.3)
Requires-Dist: ifcfactory (>=0.2.0,<0.3.0)
Requires-Dist: ifcopenshell (==0.8.4)
Requires-Dist: lxml (>=5.3.1)
Requires-Dist: numpy (>=2.3.1,<3.0.0)
Requires-Dist: openpyxl (>=3.1.5)
Requires-Dist: pandas (>=2.2.2)
Requires-Dist: pydantic (>=2.10.6)
Requires-Dist: pydantic-settings (>=2.2.1)
Requires-Dist: pyproj (>=0.0.0)
Requires-Dist: pyvista (>=0.44.2)
Requires-Dist: rasterio (>=1.4.3)
Requires-Dist: scipy (>=1.16.0,<2.0.0)
Project-URL: Homepage, https://github.com/LGV-BIM-Leitstelle/BIMFabrikHH_core
Project-URL: Repository, https://github.com/LGV-BIM-Leitstelle/BIMFabrikHH_core
